[
    {
        "id": "1|743|0|82|16032018",
        "type": "bus",
        "trainId": null,
        "lineId": "1:AVL---:CN 1",
        "line": "CN 1",
        "number": 2541,
        "departure": 1521243300,
        "delay": 0,
        "live": false,
        "departureISO": "2018-03-17T00:35:00+01:00",
        "destination": "Cents, Waassertuerm",
        "destinationId": 200406019
    },
    {
        "id": "1|750|0|82|16032018",
        "type": "bus",
        "trainId": null,
        "lineId": "1:AVL---:CN 2",
        "line": "CN 2",
        "number": 2555,
        "departure": 1521243300,
        "delay": 0,
        "live": false,
        "departureISO": "2018-03-17T00:35:00+01:00",
        "destination": "Hamilius",
        "destinationId": 200405020
    },
    {
        "id": "1|758|0|82|16032018",
        "type": "bus",
        "trainId": null,
        "lineId": "1:AVL---:CN 3",
        "line": "CN 3",
        "number": 2563,
        "departure": 1521243300,
        "delay": 0,
        "live": false,
        "departureISO": "2018-03-17T00:35:00+01:00",
        "destination": "Hamilius",
        "destinationId": 200405020
    },
    {
        "id": "1|793|0|82|16032018",
        "type": "bus",
        "trainId": null,
        "lineId": "1:AVL---:CN 4",
        "line": "CN 4",
        "number": 2705,
        "departure": 1521243300,
        "delay": 0,
        "live": false,
        "departureISO": "2018-03-17T00:35:00+01:00",
        "destination": "Hamilius",
        "destinationId": 200405020
    },
    {
        "id": "1|744|0|82|16032018",
        "type": "bus",
        "trainId": null,
        "lineId": "1:AVL---:CN 1",
        "line": "CN 1",
        "number": 2542,
        "departure": 1521243300,
        "delay": 0,
        "live": false,
        "departureISO": "2018-03-17T00:35:00+01:00",
        "destination": "Hollerich, P+R Bouillon",
        "destinationId": 200415009
    },
    {
        "id": "1|8268|0|82|17032018",
        "type": "bus",
        "trainId": null,
        "line": "CN1",
        "number": 80986,
        "departure": 1521243360,
        "delay": 60,
        "live": true,
        "departureISO": "2018-03-17T00:36:00+01:00",
        "destination": "Cents, Waassertuerm",
        "destinationId": 200406019
    },
    {
        "id": "1|6010|5|82|16032018",
        "type": "bus",
        "trainId": null,
        "lineId": "1:AVL---:CN 1",
        "line": "CN 1",
        "number": 2545,
        "departure": 1521244020,
        "delay": 0,
        "live": false,
        "departureISO": "2018-03-17T00:47:00+01:00",
        "destination": "Hollerich, P+R Bouillon",
        "destinationId": 200415009
    },
    {
        "id": "1|742|1|82|16032018",
        "type": "bus",
        "trainId": null,
        "lineId": "1:AVL---:CN 1",
        "line": "CN 1",
        "number": 2540,
        "departure": 1521244200,
        "delay": 0,
        "live": false,
        "departureISO": "2018-03-17T00:50:00+01:00",
        "destination": "Cents, Waassertuerm",
        "destinationId": 200406019
    },
    {
        "id": "1|743|1|82|16032018",
        "type": "bus",
        "trainId": null,
        "lineId": "1:AVL---:CN 1",
        "line": "CN 1",
        "number": 2541,
        "departure": 1521245100,
        "delay": 0,
        "live": false,
        "departureISO": "2018-03-17T01:05:00+01:00",
        "destination": "Cents, Waassertuerm",
        "destinationId": 200406019
    },
    {
        "id": "1|6168|0|82|17032018",
        "type": "bus",
        "trainId": null,
        "line": "CN2",
        "number": 67392,
        "departure": 1521245100,
        "delay": 0,
        "live": true,
        "departureISO": "2018-03-17T01:05:00+01:00",
        "destination": "Hamilius",
        "destinationId": 200405020
    },
    {
        "id": "1|744|1|82|16032018",
        "type": "bus",
        "trainId": null,
        "lineId": "1:AVL---:CN 1",
        "line": "CN 1",
        "number": 2542,
        "departure": 1521245100,
        "delay": 0,
        "live": false,
        "departureISO": "2018-03-17T01:05:00+01:00",
        "destination": "Hollerich, P+R Bouillon",
        "destinationId": 200415009
    },
    {
        "id": "1|751|0|82|16032018",
        "type": "bus",
        "trainId": null,
        "lineId": "1:AVL---:CN 2",
        "line": "CN 2",
        "number": 2556,
        "departure": 1521245100,
        "delay": 0,
        "live": false,
        "departureISO": "2018-03-17T01:05:00+01:00",
        "destination": "Hamilius",
        "destinationId": 200405020
    },
    {
        "id": "1|758|1|82|16032018",
        "type": "bus",
        "trainId": null,
        "lineId": "1:AVL---:CN 3",
        "line": "CN 3",
        "number": 2563,
        "departure": 1521245100,
        "delay": 0,
        "live": false,
        "departureISO": "2018-03-17T01:05:00+01:00",
        "destination": "Hamilius",
        "destinationId": 200405020
    },
    {
        "id": "1|792|0|82|16032018",
        "type": "bus",
        "trainId": null,
        "lineId": "1:AVL---:CN 4",
        "line": "CN 4",
        "number": 2704,
        "departure": 1521245100,
        "delay": 0,
        "live": false,
        "departureISO": "2018-03-17T01:05:00+01:00",
        "destination": "Hamilius",
        "destinationId": 200405020
    },
    {
        "id": "1|7224|0|82|17032018",
        "type": "bus",
        "trainId": null,
        "line": "CN1",
        "number": 74680,
        "departure": 1521245100,
        "delay": 0,
        "live": true,
        "departureISO": "2018-03-17T01:05:00+01:00",
        "destination": "Cents, Waassertuerm",
        "destinationId": 200406019
    },
    {
        "id": "1|6010|6|82|16032018",
        "type": "bus",
        "trainId": null,
        "lineId": "1:AVL---:CN 1",
        "line": "CN 1",
        "number": 2545,
        "departure": 1521245820,
        "delay": 0,
        "live": false,
        "departureISO": "2018-03-17T01:17:00+01:00",
        "destination": "Hollerich, P+R Bouillon",
        "destinationId": 200415009
    },
    {
        "id": "1|742|2|82|16032018",
        "type": "bus",
        "trainId": null,
        "lineId": "1:AVL---:CN 1",
        "line": "CN 1",
        "number": 2540,
        "departure": 1521246000,
        "delay": 0,
        "live": false,
        "departureISO": "2018-03-17T01:20:00+01:00",
        "destination": "Cents, Waassertuerm",
        "destinationId": 200406019
    },
    {
        "id": "1|7718|0|82|17032018",
        "type": "bus",
        "trainId": null,
        "line": "CN1",
        "number": 71613,
        "departure": 1521246000,
        "delay": 0,
        "live": true,
        "departureISO": "2018-03-17T01:20:00+01:00",
        "destination": "Cents, Waassertuerm",
        "destinationId": 200406019
    }
]
